lorrystream/__init__.py
lorrystream/cli.py
lorrystream/cmd.py
lorrystream/core.py
lorrystream/exceptions.py
lorrystream/model.py
lorrystream/carabas/__init__.py
lorrystream/carabas/aws/__init__.py
lorrystream/carabas/aws/model.py
lorrystream/carabas/aws/cf/__init__.py
lorrystream/carabas/aws/cf/dms_next.py
lorrystream/carabas/aws/function/__init__.py
lorrystream/carabas/aws/function/model.py
lorrystream/carabas/aws/function/oci.py
lorrystream/carabas/aws/function/zip.py
lorrystream/carabas/aws/stack/__init__.py
lorrystream/carabas/aws/stack/dms.py
lorrystream/carabas/aws/stack/dynamodb.py
lorrystream/process/__init__.py
lorrystream/process/kinesis_cratedb_lambda.py
lorrystream/spike/__init__.py
lorrystream/spike/kcl_dynamodb/__init__.py
lorrystream/spike/kcl_dynamodb/dynamodb_cdc_processor.py
lorrystream/spike/kcl_kinesis/__init__.py
lorrystream/spike/kcl_kinesis/amazon_kclpy_helper.py
lorrystream/spike/kcl_kinesis/record_processor.py
lorrystream/spike/kinesis/__init__.py
lorrystream/streamz/__init__.py
lorrystream/streamz/amqp.py
lorrystream/streamz/model.py
lorrystream/streamz/sinks.py
lorrystream/streamz/sources.py
lorrystream/util/__init__.py
lorrystream/util/about.py
lorrystream/util/aio.py
lorrystream/util/cli.py
lorrystream/util/common.py
lorrystream/util/data.py
lorrystream/util/python/__init__.py
lorrystream/util/python/bundle.py
lorrystream/util/python/pep723.py
lorrystream-0.0.9.dist-info/licenses/LICENSE
lorrystream-0.0.9.dist-info/METADATA
lorrystream-0.0.9.dist-info/WHEEL
lorrystream-0.0.9.dist-info/entry_points.txt
lorrystream-0.0.9.dist-info/top_level.txt
lorrystream-0.0.9.dist-info/RECORD
